dash_query_builder/DashQueryBuilder.py
dash_query_builder/__init__.py
dash_query_builder/__version__.py
dash_query_builder/_imports_.py
dash_query_builder/dash_query_builder.js
dash_query_builder/dash_query_builder.js.LICENSE.txt
dash_query_builder/metadata.json
dash_query_builder/package-info.json
dash_query_builder/js/async-antd-08125ffa.js
dash_query_builder/js/async-antd-5c702366.js
dash_query_builder/js/async-antd-6575d636.js
dash_query_builder/js/async-antd-6575d636.js.LICENSE.txt
dash_query_builder/js/async-antd-6ef37c4b.js
dash_query_builder/js/async-antd-6f0a41ad.js
dash_query_builder/js/async-antd-8162d906.js
dash_query_builder/js/async-antd-8162d906.js.LICENSE.txt
dash_query_builder/js/async-antd-915e7c66.js
dash_query_builder/js/async-antd-d07461da.js
dash_query_builder/js/async-antd-e139457f.js
dash_query_builder/js/async-antd-e4527a1e.js
dash_query_builder/js/async-antd-e96e9bea.js
dash_query_builder/js/async-bootstrap-5d3f7ed2.js
dash_query_builder/js/async-bootstrap-c4a691e0.js
dash_query_builder/js/async-bootstrap-e96e9bea.js
dash_query_builder/js/async-fluent-28783526.js
dash_query_builder/js/async-fluent-2d48116b.js
dash_query_builder/js/async-fluent-4e83fca6.js
dash_query_builder/js/async-fluent-4fc3981f.js
dash_query_builder/js/async-fluent-62b537ca.js
dash_query_builder/js/async-fluent-b82ab764.js
dash_query_builder/js/async-fluent-c8e5d056.js
dash_query_builder/js/async-fluent-e96e9bea.js
dash_query_builder/js/async-fluent-efef450f.js
dash_query_builder/js/async-fluent-f79ca946.js
dash_query_builder/js/async-mui-0dff58e9.js
dash_query_builder/js/async-mui-1a84984e.js
dash_query_builder/js/async-mui-919d96d0.js
dash_query_builder/js/async-mui-bootstrap.js
dash_query_builder/js/async-mui-c30f4496.js
dash_query_builder/js/async-mui-c7ba4e9c.js
dash_query_builder/js/async-mui-d1e4702f.js
dash_query_builder/js/async-mui-dcc036e9.js
dash_query_builder/js/async-mui-dcc036e9.js.LICENSE.txt
dash_query_builder/js/async-mui-e47c2213.js
dash_query_builder-1.0.0.dist-info/METADATA
dash_query_builder-1.0.0.dist-info/WHEEL
dash_query_builder-1.0.0.dist-info/licenses/LICENSE
dash_query_builder-1.0.0.dist-info/RECORD
