Metadata-Version: 2.3
Name: dash-query-builder
Version: 1.0.0
Summary: Component for Dash based on react-awesome-query-builder
Project-URL: Homepage, https://github.com/tillerburr/dash-query-builder
Project-URL: Repository, https://github.com/tillerburr/dash-query-builder
Project-URL: Issues, https://github.com/tillerburr/dash-query-builder/issues
Author-email: Tyler Baur <baur.tyler@gmail.com>
License-Expression: MIT
License-File: LICENSE
Keywords: dash,dash-query-builder
Classifier: Development Status :: 4 - Beta
Classifier: Framework :: Dash
Classifier: Intended Audience :: Developers
Classifier: License :: OSI Approved :: MIT License
Classifier: Programming Language :: Python :: 3
Classifier: Programming Language :: Python :: 3.9
Classifier: Programming Language :: Python :: 3.10
Classifier: Programming Language :: Python :: 3.11
Classifier: Programming Language :: Python :: 3.12
Requires-Python: >=3.9
Requires-Dist: dash>=2.0
Provides-Extra: test
Requires-Dist: dash[dev,testing]; extra == 'test'
Requires-Dist: pyparsing; extra == 'test'
Requires-Dist: ruff; extra == 'test'
Requires-Dist: shortuuid; extra == 'test'
Provides-Extra: where
Requires-Dist: pyparsing>=3.0.9; extra == 'where'
Requires-Dist: shortuuid>=1.0.11; extra == 'where'
